elarb/__init__.py
elarb/datasets.py
elarb/models.py
elarb/optimiser.py
elarb/util.py
elarb-0.1.0.dist-info/AUTHORS.md
elarb-0.1.0.dist-info/METADATA
elarb-0.1.0.dist-info/WHEEL
elarb-0.1.0.dist-info/top_level.txt
elarb-0.1.0.dist-info/RECORD
