Metadata-Version: 2.1
Name: elarb
Version: 0.1.0
Summary: Library for x
Requires-Python: >=3.7
License-File: AUTHORS.md
Requires-Dist: cvxpy
Requires-Dist: pandas
Requires-Dist: numpy
Provides-Extra: tests
Requires-Dist: build ; extra == 'tests'
Requires-Dist: twine ; extra == 'tests'
Requires-Dist: pytest ; extra == 'tests'
Requires-Dist: flake8 ; extra == 'tests'
